webdiv/__init__.py
webdiv/pulse.py
webdiv-0.1.2.dist-info/METADATA
webdiv-0.1.2.dist-info/WHEEL
webdiv-0.1.2.dist-info/top_level.txt
webdiv-0.1.2.dist-info/RECORD
