Metadata-Version: 2.1
Name: webdiv
Version: 0.1.2
Requires-Dist: uvicorn
